{
	"Number": "104",
	"Genre": "con",
	"GenreNumber": "n",
	"Title": "あなたは|おもしろ Flash好きですか。",
	"Starr":{
		"Gota": "Gota Shirato",
		"Uesho": "Sho Uemori"
	},
	"Topics":[
		"劇空間ぱわふるリーグのコメント欄が盛んでビックリした",
		"※動画は各自探してみてください",
		"オラサイト",
		"恋のマイアヒ",
		"Cyprien",
		"小小系列",
		"赤い部屋",
		"ゲーム",
		"俺の回が伸びない理由"
	],
    "References":{
		"おたよりコーナー": "https://forms.gle/1VjUsrk8TB1fQqL86",
		"Cyprien 日本編": "https://www.youtube.com/watch?v=s3prRmnZg3s",
		"キーボードクラッシャーの今": "https://dic.nicovideo.jp/a/%E3%82%AD%E3%83%BC%E3%83%9C%E3%83%BC%E3%83%89%E3%82%AF%E3%83%A9%E3%83%83%E3%82%B7%E3%83%A3%E3%83%BC",
		"接点t": "https://dic.nicovideo.jp/a/%E6%8E%A5%E7%82%B9t",
		"【都市伝説】2020年に遊べなくなる『伝説のFlashホラー作品』が凄い (YouTube)": "https://youtu.be/82s95sg7uQo",
		"いい町": "http://kozasa.sakura.ne.jp/town/town_maker.cgi",
		"劇空間ぱわふるリーグ": "http://kimama.sakura.ne.jp/gekipawa6/",
		"Bowman2": "http://osusumeflashgame.blog.fc2.com/blog-entry-44.html",
		"シフトアップネット": "http://www.shiftup.net/",
		"クラフトボス『Flash Back Memories』3分39秒 宮崎吐夢 サントリー": "https://youtu.be/ezF1ZJurYig",
		"QWOP": "http://www.foddy.net/Athletics.html"
	},
	"Memo":""
}